setup.py
luisatorquato/Binomialdistribution.py
luisatorquato/Gaussiandistribution.py
luisatorquato/Generaldistribution.py
luisatorquato/__init__.py
luisatorquato.egg-info/PKG-INFO
luisatorquato.egg-info/SOURCES.txt
luisatorquato.egg-info/dependency_links.txt
luisatorquato.egg-info/not-zip-safe
luisatorquato.egg-info/top_level.txt